vivaldi/__init__.py
vivaldi/call.py
vivaldi/cli.py
vivaldi/turn.py
vivaldi/types.py
vivaldi/vivaldi_pb2.py
vivaldi/vivaldi_pb2.pyi
vivaldi-0.2.4.dist-info/entry_points.txt
vivaldi-0.2.4.dist-info/LICENSE
vivaldi-0.2.4.dist-info/WHEEL
vivaldi-0.2.4.dist-info/METADATA
vivaldi-0.2.4.dist-info/RECORD
