Metadata-Version: 2.1
Name: vivaldi
Version: 0.2.4
Summary: Tools for working with VIVA data formats
License: MIT
Author: Abhinav Tushar
Author-email: abhinav@vernacular.ai
Requires-Python: >=3.8,<4.0
Classifier: License :: OSI Approved :: MIT License
Classifier: Programming Language :: Python :: 3
Classifier: Programming Language :: Python :: 3.8
Classifier: Programming Language :: Python :: 3.9
Requires-Dist: docopt (>=0.6.2,<0.7.0)
